{
    "archive.org": {
        "url": "https://archive.org/search?query=|TITLEQUERYSPACE|&and%5B%5D=lending%3A%22is_readable%22&and%5B%5D=mediatype%3A%22texts%22",
        "separator": "+",
        "language": "many"
    },
    "z-library.do": {
        "url": "https://z-library.do/s/|TITLEQUERYSPACE|/?extensions%5B0%5D=PDF&extensions%5B1%5D=EPUB",
        "separator": "%20",
        "language": "many"
    },
    "libronube.com": {
        "url": "https://www.libronube.com/dibros/?q1=|TITLEQUERYSPACE|&sin_filtrar=on",
        "separator": "+",
        "language": "spanish"
    },
    "elejandria.com": {
        "url": "https://www.elejandria.com/buscar?q=|TITLEQUERYSPACE|&from=0",
        "separator": "+",
        "language": "spanish"
    },
    "textos.info": {
        "url": "https://www.textos.info/buscar/|TITLEQUERYSPACE|?",
        "separator": "%20",
        "language": "spanish"
    },
    "lectulandia.com": {
        "url": "https://ww3.lectulandia.com/search/|TITLEQUERYSPACE|",
        "separator": "+",
        "language": "spanish"
    },
    "epublibre.xyz": {
        "url": "https://epublibre.xyz/search/|TITLEQUERYSPACE|/page/1",
        "separator": "+",
        "language": "spanish"
    },
    "epublibre.org": {
        "url": "https://www.epublibre.org/catalogo/index/0/nuevo/disponibles/sin/todos/|TITLEQUERYSPACE|",
        "separator": "%20",
        "language": "spanish"
    },
    "pdf-libros.com": {
        "url": "https://pdf-libros.com/?s=|TITLEQUERYSPACE|",
        "separator": "+",
        "language": "spanish"
    },
    "es.scribd.com": {
        "url": "https://es.scribd.com/search?query=|TITLEQUERYSPACE|&ct_lang=0&filters=%7B%22filetype%22%3A%5B%22pdf%22%2C%22epub%22%5D%7D",
        "separator": "+",
        "language": "many"
    },
    "cervantesvirtual.com": {
        "url": "https://www.cervantesvirtual.com/buscador/?tipo=palabras_todas&avanzada=1&busqueda=combinada&fformato=PDF&ttitulo=|TITLEQUERYSPACE|&orden=PONDERACION&limit=50",
        "separator": "+",
        "language": "many"
    },
    "gutenberg.org": {
        "url": "https://www.gutenberg.org/ebooks/search/?query=|TITLEQUERYSPACE|&submit_search=Go%21",
        "separator": "+",
        "language": "many"
    },
    "hathitrust.org": {
        "url": "https://babel.hathitrust.org/cgi/ls?lmt=ft&a=srchls&adv=1&q1=|TITLEQUERYSPACE|&field1=ocr&anyall1=all&op1=AND&facet_format=format%3ABook&facet_format=format%3APhotographs+%26+Pictorial+Works&facet_format=format%3ANewspaper&facet_format=format%3AManuscript&facet_format=format%3AJournal&facet_format=format%3AEncyclopedias&facet_format=format%3ADictionaries&facet_format=format%3AUnknown&facet_format=format%3ASerial&facet_format=format%3AMaps-Atlas&facet_format=format%3AMap&facet_format=format%3ABiography&facet_format=format%3AMicroform",
        "separator": "+",
        "language": "many"
    },
    "rae.es": {
        "url": "https://www.rae.es/biblioteca-digital/buscador?key=|TITLEQUERYSPACE|",
        "separator": "+",
        "language": "spanish"
    },
    "pdfdrive.com": {
        "url": "https://www.pdfdrive.com/search?q=|TITLEQUERYSPACE|&pagecount=&pubyear=&searchin=&em=0",
        "separator": "+",
        "language": "many"
    },
    "google.com": {
        "url": "https://www.google.com/search?tbo=p&tbm=bks&q=intitle:|TITLEQUERYSPACE|&tbs=,bkv:f&num=100",
        "separator": "+intitle:",
        "language": "many"
    },
    "es.wikisource.org": {
        "url": "https://es.wikisource.org/wiki/|TITLEQUERYSPACE|",
        "separator": "_",
        "language": "spanish"
    }
}